shell_pilot/__init__.py
shell_pilot/py.typed
shell_pilot-0.3.1.dist-info/WHEEL
shell_pilot-0.3.1.dist-info/METADATA
shell_pilot-0.3.1.dist-info/RECORD
