Metadata-Version: 2.4
Name: shell-pilot
Version: 0.3.1
Summary: A more ergonomic subprocess alternative with bash-like pipe syntax
Keywords: subprocess,shell,pipe,bash,command,process
Author: Nick Rogers
Author-email: Nick Rogers <nick.rogers@wagestream.co.uk>
License-Expression: MIT
Classifier: Development Status :: 4 - Beta
Classifier: Intended Audience :: Developers
Classifier: License :: OSI Approved :: MIT License
Classifier: Operating System :: OS Independent
Classifier: Programming Language :: Python :: 3
Classifier: Programming Language :: Python :: 3.9
Classifier: Programming Language :: Python :: 3.10
Classifier: Programming Language :: Python :: 3.11
Classifier: Programming Language :: Python :: 3.12
Classifier: Programming Language :: Python :: 3.13
Classifier: Topic :: Software Development :: Libraries :: Python Modules
Classifier: Topic :: System :: Shells
Classifier: Typing :: Typed
Requires-Python: >=3.9
Project-URL: Homepage, https://github.com/rogersnm/shell-pilot
Project-URL: Issues, https://github.com/rogersnm/shell-pilot/issues
Project-URL: Repository, https://github.com/rogersnm/shell-pilot
